dwavetikz/__init__.py
dwavetikz/_generate.py
dwavetikz/chimera.py
dwavetikz/cli.py
dwavetikz/pegasus.py
dwavetikz/render.py
dwavetikz/zephyr.py
dwavetikz/templates/base.jinja2
dwavetikz/templates/chimera.jinja2
dwavetikz/templates/pegasus.jinja2
dwavetikz/templates/zephyr.jinja2
pictures/chimera.svg
pictures/chimera2.svg
pictures/chimera3.svg
pictures/chimera4.svg
pictures/pegasus.svg
pictures/pegasus2.svg
pictures/zephyr.svg
dwave_tikz-0.0.2.dist-info/METADATA
dwave_tikz-0.0.2.dist-info/WHEEL
dwave_tikz-0.0.2.dist-info/entry_points.txt
dwave_tikz-0.0.2.dist-info/top_level.txt
dwave_tikz-0.0.2.dist-info/RECORD
