Metadata-Version: 2.1
Name: dwave-tikz
Version: 0.0.2
Summary: Tools for generating pictures for various D-Wave topologies
Author-email: Konrad Jałowiecki <dexter2206@gmail.com>
License: MIT
Project-URL: Source Code, https://github.com/dexter2206/dwave-tikz
Classifier: Intended Audience :: Science/Research
Classifier: License :: OSI Approved :: MIT License
Classifier: Programming Language :: Python :: 3
Classifier: Topic :: Scientific/Engineering :: Physics
Requires-Python: >=3.8
Requires-Dist: dwave-networkx (~=0.8.13)
Requires-Dist: jinja2 (~=3.1.2)
Provides-Extra: dev
Requires-Dist: flake8 (>=4.0.1) ; extra == 'dev'
Requires-Dist: black (>=21.12b0) ; extra == 'dev'
Requires-Dist: isort (>=5.10.1) ; extra == 'dev'
Requires-Dist: mypy (>=0.961) ; extra == 'dev'
Provides-Extra: test
Requires-Dist: pytest (>=6.1.2) ; extra == 'test'
Requires-Dist: pytest-mock (>=3.3.1) ; extra == 'test'
Requires-Dist: pytest-cov (>=2.12.1) ; extra == 'test'
